{
    "scripts": {
        "start": {
            "cmd": "deno run server.ts",
            "desc": "Run the server.",
            "allow": [
                "all"
            ]
        },
        "init": {
            "cmd": "deno cache --lock=packages.json --lock-write packages.ts",
            "desc": "create lock file"
           },
        "reinit": {
            "cmd": "deno cache --reload --lock=packages.json --lock-write packages.ts",
            "desc": "create lock file with force reload"
        }
    },
    "files": ["server.ts"],
    "watcher": {
        "interval": 350,
        "exts": ["js", "ts", "json"],
        "match": ["*.*"],
        "skip": ["*/.git/*"],
        "legacy": false
    },
    "execute": {
        ".js": ["deno", "run"],
        ".ts": ["deno", "run"]
    },
    "test": true
}